cqlib_qschool-0.1.0.dist-info/licenses/LICENSE
qschool/VERSION.txt
qschool/__init__.py
qschool/_version.py
qschool/qschool.py
cqlib_qschool-0.1.0.dist-info/METADATA
cqlib_qschool-0.1.0.dist-info/WHEEL
cqlib_qschool-0.1.0.dist-info/top_level.txt
cqlib_qschool-0.1.0.dist-info/RECORD
