Metadata-Version: 2.4
Name: cqlib-qschool
Version: 0.1.0
Summary: Cqlib qschool
Author-email: Gao Jianjian <jianjian001@outlook.com>
License-Expression: Apache-2.0
Keywords: cqlib,cqlib adapter,quantum circuit,quantum computing,quantum programming language,quantum,sdk
Classifier: Environment :: Console
Classifier: Operating System :: MacOS
Classifier: Operating System :: Microsoft :: Windows
Classifier: Operating System :: POSIX :: Linux
Classifier: Programming Language :: Python :: 3 :: Only
Classifier: Programming Language :: Python :: 3.10
Classifier: Programming Language :: Python :: 3.11
Classifier: Programming Language :: Python :: 3.12
Classifier: Programming Language :: Python :: 3.13
Classifier: Topic :: Software Development :: Libraries
Requires-Python: >=3.10
License-File: LICENSE
Requires-Dist: cqlib>=1.3.0
Dynamic: license-file
